pyramid_selectauth/__init__.py
pyramid_selectauth/policy.py
pyramid_selectauth/tests.py
pyramid_selectauth-1.0.1.dist-info/METADATA
pyramid_selectauth-1.0.1.dist-info/RECORD
pyramid_selectauth-1.0.1.dist-info/WHEEL
pyramid_selectauth-1.0.1.dist-info/top_level.txt
