Metadata-Version: 2.1
Name: pyramid-selectauth
Version: 1.0.1
Summary: pyramid_selectauth
Home-page: https://github.com/OvalMoney/pyramid_selectauth
Author: Walter Danilo Galante
Author-email: walter.galante@ovalmoney.com
License: UNKNOWN
Keywords: web pyramid pylons authentication
Platform: UNKNOWN
Classifier: Programming Language :: Python
Classifier: Framework :: Pylons
Classifier: Topic :: Internet :: WWW/HTTP
Classifier: License :: OSI Approved :: Mozilla Public License 2.0 (MPL 2.0)
Requires-Dist: pyramid
